alkindi/__init__.py
alkindi/_liboqs.abi3.so
alkindi/bindings.py
alkindi/core.py
alkindi/kem.py
alkindi/signatures.py
alkindi-0.1.3.dist-info/METADATA
alkindi-0.1.3.dist-info/WHEEL
alkindi-0.1.3.dist-info/top_level.txt
alkindi-0.1.3.dist-info/RECORD
alkindi-0.1.3.dist-info/licenses/LICENSE
