Metadata-Version: 2.4
Name: alkindi
Version: 0.1.3
Summary: A Python library for post-quantum cryptographic algorithms
Home-page: https://github.com/alraddady/alkindi
Author: Khalid Alraddady
Author-email: k.alraddady@outlook.sa
License: LGPL-3.0-or-later
Requires-Python: >=3.10
License-File: LICENSE
Requires-Dist: cffi>=1.15
Provides-Extra: dev
Requires-Dist: pytest; extra == "dev"
Dynamic: author
Dynamic: author-email
Dynamic: description
Dynamic: description-content-type
Dynamic: home-page
Dynamic: license
Dynamic: license-file
Dynamic: provides-extra
Dynamic: requires-dist
Dynamic: requires-python
Dynamic: summary
